{
  "assicurazioneDurataFurto": "",
  "kwVettura": "85",
  "nomeVetturaInp": "VOLKSWAGEN T-Roc",
  "linkImmagine4": "https://autolazeta.it/wp-content/uploads/2025/07/22606427_O_chmfxpr1y4vzi.jpg",
  "tecnologia": "Diesel",
  "legge104": "0",
  "data": "",
  "servicesAnticipo": "0",
  "notePreventivo": "",
  "linkImmagine1": "https://autolazeta.it/wp-content/uploads/2025/07/22606427_O_7qu3xcymowvgf.jpg",
  "operatore": "Marco Lazeta",
  "targaInput": "GL991NX",
  "provinciaResidenza": "",
  "linkImmagine5": "https://autolazeta.it/wp-content/uploads/2025/07/22606427_O_hd61ir4olyapm.jpg",
  "cilindrataKwBatteria": "1968",
  "servicesTan": "9.5",
  "supplementoGaranzia": "0",
  "assicurazioneImportoFurto": "",
  "valorePermuta": "",
  "P2": "750",
  "sottotitoloVettura": "2.0 TDI SCR Life",
  "dettagliPermuta": "",
  "nomeVettura": "VOLKSWAGEN T-Roc",
  "annoImmatricolazione": "2023",
  "finanziamentoServiziAttivo": "0",
  "servicesPdp": "0",
  "free1": "",
  "cognomeCliente": "",
  "linkImmagine3": "https://autolazeta.it/wp-content/uploads/2025/07/22606427_O_v790mqgnu2oad.jpg",
  "optionalSpecialeNome": "",
  "optionalSpecialeImporto": "",
  "assicurazioneImporto": "",
  "nomeCliente": "",
  "cambioAutomatico": "0",
  "scontoImporto": "",
  "assicurazioneDurata": "",
  "optionalDotazioni": "IQ.DRIVE, FARI A LED CON ABBAGLIANTI AUTOMATICI E LUCI DIURNE, RICONOSCIMENTO DELLA SEGNALETICA STRADALE, LANE ASSIST-CONTROLLO ELETTRONICO DELLA CORSIA, FRONT ASSIST-FRENATA D'EMERGENZA ASSISTITA, SIDE ASSIST-MONITORAGGIO ANGOLO CIECO CON ASSISTENTE IN RETROMARCIA, ADAPTIVE CRUISE CONTROL CON SISTEMA DI AVVISO DI DISTANZA, PARK DISTANCE CONTROL CON SENSORI DI PARCHEGGIO A 360°, SISTEMA DI PARCHEGGIO AUTOMATICO, SEDILI CON SUPPORTO LOMBARE, VOLANTE IN PELLE MULTIFUNZIONE, ANDROID AUTO E APPLE CARPLAY, DAB, START&STOP, ECC...",
  "T2": "280",
  "tipologiaAutocarro": "NO",
  "servicesDurata": "36",
  "personalizzato": "",
  "valoreVettura": "21590",
  "optionalPreventivoValue": "",
  "classeAuto": "Standard",
  "infoPrincipali": "UNICO proprietario.\nREVISIONE valida fino al 03/2027.\nTELAIO: WVGZZZA1ZPV628896.\nTARGA: GL991NX.\nEURO 6d isc-fcm.\nIdonea per NEOPATENTATI.\nCOLORE: PYRIT SILBER.",
  "linkImmagine2": "https://autolazeta.it/wp-content/uploads/2025/07/22606427_O_lv7enxqwbju9d.jpg"
}